{
  "db_name": "PostgreSQL",
  "query": "SELECT guild_id, key_channel_id, key_message_id FROM guild_encryption WHERE encrypted = true AND key_channel_id IS NOT NULL AND key_message_id IS NOT NULL",
  "describe": {
    "columns": [
      {
        "ordinal": 0,
        "name": "guild_id",
        "type_info": "Int8"
      },
      {
        "ordinal": 1,
        "name": "key_channel_id",
        "type_info": "Int8"
      },
      {
        "ordinal": 2,
        "name": "key_message_id",
        "type_info": "Int8"
      }
    ],
    "parameters": {
      "Left": []
    },
    "nullable": [
      false,
      true,
      true
    ]
  },
  "hash": "a0a0771c7022fbc1581201e6682e24166875e1efe04f30bf7296006154a4503b"
}
